HandTrackingModule/__init__.py
HandTrackingModule-0.2.dist-info/METADATA
HandTrackingModule-0.2.dist-info/WHEEL
HandTrackingModule-0.2.dist-info/top_level.txt
HandTrackingModule-0.2.dist-info/RECORD
